FTPsubsetMO/__init__.py
FTPsubsetMO/__main__.py
FTPsubsetMO/Database/CMEMS_Database.json
FTPsubsetMO/Database/datasets_MY.pdf
FTPsubsetMO/IMAGES/LOGO.gif
FTPsubsetMO/Script/CMEMS_Database.json
FTPsubsetMO/Script/FTPsubsetMO.py
FTPsubsetMO-0.5.6.dist-info/LICENSE
FTPsubsetMO-0.5.6.dist-info/METADATA
FTPsubsetMO-0.5.6.dist-info/WHEEL
FTPsubsetMO-0.5.6.dist-info/entry_points.txt
FTPsubsetMO-0.5.6.dist-info/top_level.txt
FTPsubsetMO-0.5.6.dist-info/RECORD
