Metadata-Version: 2.1
Name: FTPsubsetMO
Version: 0.5.6
Summary: Python module able to download a file from FTP and subset it using time-range,bounding-box,variables and depths
Home-page: https://github.com/carmelosammarco/FTPsubsetMO
Author: Carmelo Sammarco
Author-email: sammarcocarmelo@gmail.com
License: gpl-3.0
Platform: OS Independent
Classifier: Development Status :: 3 - Alpha
Classifier: Intended Audience :: Science/Research
Classifier: Topic :: Scientific/Engineering
Classifier: Programming Language :: Python :: 3.6
Requires-Python: >=3
Requires-Dist: ftputil (>=3.4)
Requires-Dist: netCDF4 (>=1.4.2)
Requires-Dist: pandas (>=0.23.4)
Requires-Dist: xarray (>=0.11.0)
Requires-Dist: json5 (>=0.9.1)
Requires-Dist: h5py (>=2.10.0)
Requires-Dist: h5netcdf (>=0.8.0)
